agentbeacon/__init__.py
agentbeacon/main.py
agentbeacon-0.1.0.dist-info/licenses/LICENSE
agentbeacon-0.1.0.dist-info/METADATA
agentbeacon-0.1.0.dist-info/WHEEL
agentbeacon-0.1.0.dist-info/entry_points.txt
agentbeacon-0.1.0.dist-info/top_level.txt
agentbeacon-0.1.0.dist-info/RECORD
