Metadata-Version: 2.4
Name: agentbeacon
Version: 0.1.0
Summary: Semantic code search for AI agents via Model Context Protocol
Author-email: Adrian Quiroga <git@adrq.net>
License-Expression: MIT
Requires-Python: >=3.10
License-File: LICENSE
Requires-Dist: fastmcp>=2.11.3
Requires-Dist: pre-commit>=4.3.0
Dynamic: license-file
